{"duration":4959,"records":[{"duration":3481,"stepId":"io.quarkus.kafka.client.deployment.DevServicesKafkaProcessor#startKafkaDevService","started":"15:28:34.320","dependents":[393,388],"id":387,"thread":"build-39"},{"duration":2035,"stepId":"io.quarkus.kubernetes.deployment.KubernetesProcessor#build","started":"15:28:33.839","dependents":[386],"id":385,"thread":"build-66"},{"duration":719,"stepId":"io.quarkus.kubernetes.client.deployment.DevServicesKubernetesProcessor#setupKubernetesDevService","started":"15:28:34.320","dependents":[393,388],"id":384,"thread":"build-7"},{"duration":611,"stepId":"io.quarkus.vertx.http.deployment.devmode.console.DevConsoleProcessor#setupDeploymentSideHandling","started":"15:28:37.818","dependents":[409,410],"id":408,"thread":"build-39"},{"duration":554,"stepId":"io.quarkus.deployment.index.ApplicationArchiveBuildStep#build","started":"15:28:33.723","dependents":[312,269,376,383,315,372,286,317,328,318,361,308,270,320,273,305,272],"id":268,"thread":"build-3"},{"duration":266,"stepId":"io.quarkus.deployment.ide.IdeProcessor#detectRunningIdeProcesses","started":"15:28:33.604","dependents":[265],"id":264,"thread":"build-27"},{"duration":250,"stepId":"io.quarkus.vertx.http.deployment.webjar.WebJarProcessor#processWebJarDevMode","started":"15:28:33.612","dependents":[413,397,263],"id":262,"thread":"build-16"},{"duration":173,"stepId":"io.quarkus.kubernetes.deployment.OpenshiftProcessor#createDecorators","started":"15:28:33.666","dependents":[385],"id":261,"thread":"build-18"},{"duration":169,"stepId":"io.quarkus.kubernetes.deployment.VanillaKubernetesProcessor#createDecorators","started":"15:28:33.667","dependents":[385],"id":260,"thread":"build-66"},{"duration":157,"stepId":"io.quarkus.deployment.console.ConsoleProcessor#setupConsole","started":"15:28:33.611","dependents":[384,267,259,387,305],"id":258,"thread":"build-39"},{"duration":110,"stepId":"io.quarkus.deployment.steps.ApplicationIndexBuildStep#build","started":"15:28:33.612","dependents":[257,268,349,337],"id":256,"thread":"build-65"},{"duration":105,"stepId":"io.quarkus.deployment.steps.ConfigDescriptionBuildStep#createConfigDescriptions","started":"15:28:33.614","dependents":[392,408],"id":255,"thread":"build-57"},{"duration":100,"stepId":"io.quarkus.deployment.steps.MainClassBuildStep#build","started":"15:28:38.431","dependents":[],"id":413,"thread":"build-66"},{"duration":96,"stepId":"io.quarkus.deployment.steps.ConfigGenerationBuildStep#generateConfigClass","started":"15:28:37.807","dependents":[412],"id":407,"thread":"build-62"},{"duration":92,"stepId":"io.quarkus.kafka.client.deployment.KafkaProcessor#registerKafkaUiExecHandler","started":"15:28:33.585","dependents":[413,397,408],"id":236,"thread":"build-15"},{"duration":89,"stepId":"org.apache.camel.quarkus.core.deployment.CamelProcessor#createModelToXMLDumper","started":"15:28:33.580","dependents":[413,377],"id":215,"thread":"build-8"},{"duration":89,"stepId":"org.apache.camel.quarkus.core.deployment.CamelContextProcessor#devModeCamelContextCustomizations","started":"15:28:33.587","dependents":[413,377],"id":235,"thread":"build-7"},{"duration":87,"stepId":"io.quarkus.arc.deployment.ArcProcessor#registerBeans","started":"15:28:34.365","dependents":[381,346,348,340,345,351,339,347,342,349,353,382,341,352,354,344,343],"id":338,"thread":"build-45"},{"duration":87,"stepId":"io.quarkus.deployment.dev.io.NioThreadPoolDevModeProcessor#setupTCCL","started":"15:28:33.578","dependents":[413],"id":205,"thread":"build-2"},{"duration":84,"stepId":"io.quarkus.vertx.http.deployment.devmode.ArcDevProcessor#eventsEndpoint","started":"15:28:33.593","dependents":[413,397,408],"id":238,"thread":"build-22"},{"duration":84,"stepId":"io.quarkus.vertx.core.deployment.VertxCoreProcessor#ioThreadDetector","started":"15:28:33.587","dependents":[413,230],"id":224,"thread":"build-10"},{"duration":81,"stepId":"org.apache.camel.quarkus.core.deployment.CamelRegistryProcessor#registry","started":"15:28:33.597","dependents":[413,383,377,402],"id":239,"thread":"build-3"},{"duration":78,"stepId":"org.apache.camel.quarkus.core.deployment.CamelProcessor#createJaxbContextFactory","started":"15:28:33.594","dependents":[413,377],"id":227,"thread":"build-1"},{"duration":77,"stepId":"org.apache.camel.quarkus.component.platform.http.deployment.PlatformHttpProcessor#platformHttpEngine","started":"15:28:33.587","dependents":[413,212,242],"id":204,"thread":"build-12"},{"duration":75,"stepId":"io.quarkus.deployment.steps.PreloadClassesBuildStep#preInit","started":"15:28:33.592","dependents":[413],"id":210,"thread":"build-21"},{"duration":75,"stepId":"io.quarkus.deployment.logging.LoggingResourceProcessor#logConsoleCommand","started":"15:28:33.604","dependents":[395],"id":244,"thread":"build-14"},{"duration":70,"stepId":"io.quarkus.vertx.core.deployment.VertxCoreProcessor#createVertxThreadFactory","started":"15:28:33.600","dependents":[413,243],"id":225,"thread":"build-32"},{"duration":66,"stepId":"io.quarkus.arc.deployment.ArcProcessor#generateResources","started":"15:28:34.485","dependents":[413,376,367,412],"id":366,"thread":"build-59"},{"duration":66,"stepId":"io.quarkus.deployment.steps.BootstrapConfigSetupBuildStep#setupBootstrapConfig","started":"15:28:33.596","dependents":[413,207],"id":201,"thread":"build-26"},{"duration":66,"stepId":"io.quarkus.vertx.http.deployment.devmode.ArcDevProcessor#invocationsEndpoint","started":"15:28:33.609","dependents":[413,397,408],"id":234,"thread":"build-50"},{"duration":66,"stepId":"org.apache.camel.quarkus.component.rest.deployment.RestProcessor#customizeCamelContext","started":"15:28:33.603","dependents":[413,377],"id":216,"thread":"build-25"},{"duration":65,"stepId":"org.apache.camel.quarkus.core.deployment.CamelProcessor#packageScanClassResolver","started":"15:28:33.605","dependents":[413,377],"id":226,"thread":"build-44"},{"duration":65,"stepId":"io.quarkus.smallrye.context.deployment.SmallRyeContextPropagationProcessor#buildStatic","started":"15:28:33.613","dependents":[413],"id":240,"thread":"build-17"},{"duration":65,"stepId":"io.quarkus.mutiny.deployment.MutinyProcessor#buildTimeInit","started":"15:28:33.595","dependents":[413],"id":197,"thread":"build-24"},{"duration":65,"stepId":"io.quarkus.vertx.core.deployment.VertxCoreProcessor#createVertxContextHandlers","started":"15:28:33.605","dependents":[413,246,243],"id":220,"thread":"build-11"},{"duration":64,"stepId":"org.apache.camel.quarkus.core.deployment.main.CamelMainProcessor#routesLoader","started":"15:28:33.612","dependents":[413,247],"id":237,"thread":"build-51"},{"duration":63,"stepId":"io.quarkus.resteasy.deployment.ResteasyStandaloneBuildStep#addDefaultAuthFailureHandler","started":"15:28:33.610","dependents":[404,413],"id":232,"thread":"build-28"},{"duration":63,"stepId":"io.quarkus.netty.deployment.NettyProcessor#setNettyMachineId","started":"15:28:33.595","dependents":[413],"id":193,"thread":"build-4"},{"duration":62,"stepId":"io.quarkus.deployment.console.ConsoleProcessor#quitCommand","started":"15:28:33.587","dependents":[395],"id":186,"thread":"build-9"},{"duration":61,"stepId":"io.quarkus.deployment.steps.ConfigGenerationBuildStep#buildTimeRunTimeConfig","started":"15:28:33.609","dependents":[407,412],"id":222,"thread":"build-47"},{"duration":59,"stepId":"org.apache.camel.quarkus.core.deployment.CamelUnremovableBeansProcessor#unremovableCamelBeans","started":"15:28:34.293","dependents":[356,358],"id":336,"thread":"build-45"},{"duration":58,"stepId":"io.quarkus.deployment.steps.ConfigBuildSteps#generateConfigSources","started":"15:28:33.604","dependents":[],"id":200,"thread":"build-38"},{"duration":57,"stepId":"io.quarkus.kafka.client.deployment.KafkaProcessor#loadSnappyIfEnabled","started":"15:28:33.607","dependents":[413],"id":206,"thread":"build-45"},{"duration":55,"stepId":"io.quarkus.resteasy.deployment.ResteasyBuiltinsProcessor#setupExceptionMapper","started":"15:28:33.614","dependents":[330,413],"id":217,"thread":"build-43"},{"duration":55,"stepId":"io.quarkus.vertx.http.deployment.devmode.console.DevConsoleProcessor#handler","started":"15:28:33.612","dependents":[413,397,327],"id":214,"thread":"build-33"},{"duration":55,"stepId":"io.quarkus.vertx.deployment.VertxProcessor#currentContextFactory","started":"15:28:33.612","dependents":[413,366],"id":211,"thread":"build-49"},{"duration":54,"stepId":"io.quarkus.netty.deployment.NettyProcessor#eagerlyInitClass","started":"15:28:33.611","dependents":[413],"id":209,"thread":"build-60"},{"duration":53,"stepId":"io.quarkus.deployment.logging.LoggingResourceProcessor#registerMetrics","started":"15:28:33.612","dependents":[413,327],"id":208,"thread":"build-48"},{"duration":52,"stepId":"io.quarkus.deployment.steps.ConfigGenerationBuildStep#setupConfigOverride","started":"15:28:33.605","dependents":[],"id":194,"thread":"build-41"},{"duration":51,"stepId":"io.quarkus.arc.deployment.devconsole.ArcDevConsoleProcessor#exposeArcContainer","started":"15:28:33.612","dependents":[409,413],"id":203,"thread":"build-46"},{"duration":50,"stepId":"org.apache.camel.quarkus.core.deployment.CamelNativeImageProcessor#camelRuntimeCatalog","started":"15:28:34.278","dependents":[329],"id":328,"thread":"build-57"},{"duration":49,"stepId":"io.quarkus.resteasy.deployment.ResteasyBuiltinsProcessor#addReactiveRoutesExceptionMapper","started":"15:28:33.614","dependents":[413],"id":202,"thread":"build-55"},{"duration":49,"stepId":"io.quarkus.deployment.steps.ConfigGenerationBuildStep#watchConfigFiles","started":"15:28:33.610","dependents":[223],"id":195,"thread":"build-18"},{"duration":48,"stepId":"io.quarkus.deployment.console.ConsoleProcessor#helpCommand","started":"15:28:33.601","dependents":[395],"id":187,"thread":"build-29"},{"duration":48,"stepId":"io.quarkus.arc.deployment.ArcProcessor#quarkusMain","started":"15:28:33.603","dependents":[337,320,189],"id":188,"thread":"build-36"},{"duration":47,"stepId":"io.quarkus.kubernetes.deployment.KnativeProcessor#createConfigurators","started":"15:28:33.607","dependents":[385],"id":191,"thread":"build-5"},{"duration":46,"stepId":"io.quarkus.vertx.http.deployment.devmode.console.DevConsoleProcessor#collectTemplates","started":"15:28:33.602","dependents":[408],"id":185,"thread":"build-37"},{"duration":45,"stepId":"io.quarkus.kubernetes.deployment.VanillaKubernetesProcessor#createConfigurators","started":"15:28:33.609","dependents":[385],"id":190,"thread":"build-13"},{"duration":42,"stepId":"org.apache.camel.quarkus.core.deployment.CamelProcessor#factoryFinderResolver","started":"15:28:34.307","dependents":[413,377],"id":331,"thread":"build-59"},{"duration":42,"stepId":"org.apache.camel.quarkus.core.deployment.CamelProcessor#disableXmlReifiers","started":"15:28:33.633","dependents":[413],"id":233,"thread":"build-58"},{"duration":41,"stepId":"io.quarkus.deployment.DockerStatusProcessor#IsDockerWorking","started":"15:28:33.605","dependents":[384,393,387],"id":184,"thread":"build-42"},{"duration":40,"stepId":"io.quarkus.resteasy.common.deployment.ResteasyCommonProcessor#setupProviders","started":"15:28:34.308","dependents":[356,332,358,412],"id":330,"thread":"build-18"},{"duration":39,"stepId":"io.quarkus.deployment.logging.LoggingResourceProcessor#setMinLevelForInitialConfigurator","started":"15:28:33.606","dependents":[413],"id":182,"thread":"build-40"},{"duration":38,"stepId":"io.quarkus.vertx.http.deployment.devmode.tests.TestsProcessor#setupTestRoutes","started":"15:28:33.639","dependents":[413,259,398,408,400],"id":241,"thread":"build-35"},{"duration":37,"stepId":"io.quarkus.deployment.logging.LoggingResourceProcessor#setupLoggingStaticInit","started":"15:28:33.625","dependents":[413],"id":198,"thread":"build-62"},{"duration":35,"stepId":"org.apache.camel.quarkus.core.deployment.CamelProcessor#userServicePatterns","started":"15:28:33.611","dependents":[328,318,383],"id":183,"thread":"build-54"},{"duration":34,"stepId":"io.quarkus.deployment.logging.LoggingResourceProcessor#setupLoggingRuntimeInit","started":"15:28:34.285","dependents":[384,413,397,408,387,406,412],"id":327,"thread":"build-62"},{"duration":32,"stepId":"io.quarkus.arc.deployment.CommandLineArgumentsProcessor#commandLineArgs","started":"15:28:33.579","dependents":[351,337,353,352,320],"id":118,"thread":"build-6"},{"duration":30,"stepId":"io.quarkus.arc.deployment.ConfigBuildStep#registerConfigRootsAsBeans","started":"15:28:33.612","dependents":[351,353,352],"id":181,"thread":"build-34"},{"duration":30,"stepId":"io.quarkus.vertx.http.deployment.HttpSecurityProcessor#setupAuthenticationMechanisms","started":"15:28:33.639","dependents":[404,413,337,320,366],"id":219,"thread":"build-19"},{"duration":30,"stepId":"io.quarkus.vertx.http.deployment.VertxHttpProcessor#bodyHandler","started":"15:28:33.670","dependents":[404,401,413,397],"id":253,"thread":"build-2"},{"duration":29,"stepId":"io.quarkus.vertx.http.deployment.HttpSecurityProcessor#builtins","started":"15:28:33.609","dependents":[337,219,320],"id":177,"thread":"build-35"},{"duration":29,"stepId":"io.quarkus.vertx.deployment.VertxProcessor#autoAddScope","started":"15:28:33.594","dependents":[326],"id":158,"thread":"build-23"},{"duration":28,"stepId":"org.apache.camel.quarkus.core.deployment.CamelProcessor#camelServices","started":"15:28:34.278","dependents":[319,331],"id":318,"thread":"build-39"},{"duration":27,"stepId":"io.quarkus.container.image.deployment.ContainerImageProcessor#publishImageInfo","started":"15:28:33.633","dependents":[261,199,260,213],"id":196,"thread":"build-59"},{"duration":24,"stepId":"org.apache.camel.quarkus.core.deployment.CamelRegistryProcessor#bindBeansToRegistry","started":"15:28:34.558","dependents":[413],"id":383,"thread":"build-50"},{"duration":23,"stepId":"io.quarkus.arc.deployment.BeanArchiveProcessor#build","started":"15:28:34.285","dependents":[330,332,325,321,337,346,323,326,322,345],"id":320,"thread":"build-7"},{"duration":23,"stepId":"io.quarkus.kubernetes.deployment.KnativeProcessor#checkKnative","started":"15:28:33.614","dependents":[261,199,260,180],"id":176,"thread":"build-19"},{"duration":22,"stepId":"org.apache.camel.quarkus.component.json.path.deployment.JsonPathProcessor#registerReflectiveClassBuildItems","started":"15:28:33.608","dependents":[412],"id":162,"thread":"build-30"},{"duration":19,"stepId":"io.quarkus.deployment.steps.BannerProcessor#recordBanner","started":"15:28:33.670","dependents":[413,327],"id":252,"thread":"build-62"},{"duration":19,"stepId":"io.quarkus.deployment.pkg.steps.FileSystemResourcesBuildStep#notNormalMode","started":"15:28:35.875","dependents":[],"id":386,"thread":"build-7"},{"duration":19,"stepId":"io.quarkus.vertx.http.deployment.VertxHttpProcessor#additionalBeans","started":"15:28:33.611","dependents":[337,320],"id":161,"thread":"build-6"},{"duration":18,"stepId":"io.quarkus.vertx.http.deployment.StaticResourcesProcessor#collectStaticResources","started":"15:28:34.278","dependents":[373],"id":317,"thread":"build-18"},{"duration":18,"stepId":"io.quarkus.deployment.steps.CapabilityAggregationStep#aggregateCapabilities","started":"15:28:33.614","dependents":[173,164,269,271,260,213,371,317,166,168,174,330,285,172,167,261,169,303,372,219,233,309,337,334,196,175,280,385,165,170],"id":163,"thread":"build-53"},{"duration":17,"stepId":"io.quarkus.vertx.http.deployment.devmode.console.DevConsoleProcessor#setupConsole","started":"15:28:33.639","dependents":[409,410],"id":192,"thread":"build-66"},{"duration":16,"stepId":"io.quarkus.arc.deployment.ArcProcessor#validate","started":"15:28:34.467","dependents":[359,362,361,365,358,376,357,366,360,364],"id":356,"thread":"build-3"},{"duration":15,"stepId":"org.apache.camel.quarkus.core.deployment.CamelProcessor#typeConverterRegistry","started":"15:28:34.281","dependents":[413,377,412],"id":315,"thread":"build-3"},{"duration":15,"stepId":"io.quarkus.arc.deployment.SplitPackageProcessor#splitPackageDetection","started":"15:28:34.278","dependents":[366],"id":312,"thread":"build-27"},{"duration":14,"stepId":"io.quarkus.deployment.steps.DevModeBuildStep#watchChanges","started":"15:28:33.625","dependents":[223],"id":178,"thread":"build-66"},{"duration":14,"stepId":"io.quarkus.deployment.dev.testing.TestTracingProcessor#testConsoleCommand","started":"15:28:34.282","dependents":[395],"id":316,"thread":"build-59"},{"duration":14,"stepId":"io.quarkus.vertx.http.deployment.VertxHttpProcessor#frameworkRoot","started":"15:28:33.625","dependents":[404,192,397,241,408,364,263,400],"id":179,"thread":"build-64"},{"duration":14,"stepId":"io.quarkus.arc.deployment.ArcProcessor#initialize","started":"15:28:34.350","dependents":[365,338],"id":337,"thread":"build-59"},{"duration":13,"stepId":"io.quarkus.vertx.http.deployment.VertxHttpProcessor#preinitializeRouter","started":"15:28:33.687","dependents":[351,413,353,352,400],"id":254,"thread":"build-3"},{"duration":13,"stepId":"org.apache.camel.quarkus.component.platform.http.deployment.PlatformHttpProcessor#platformHttpComponentBean","started":"15:28:33.666","dependents":[413,402],"id":242,"thread":"build-55"},{"duration":13,"stepId":"io.quarkus.deployment.steps.ConfigGenerationBuildStep#checkForBuildTimeConfigChange","started":"15:28:33.669","dependents":[413],"id":248,"thread":"build-45"},{"duration":13,"stepId":"org.apache.camel.quarkus.core.deployment.CamelNativeImageProcessor#reflectiveItems","started":"15:28:34.282","dependents":[412],"id":313,"thread":"build-51"},{"duration":13,"stepId":"io.quarkus.devservices.deployment.DevServicesProcessor#config","started":"15:28:37.803","dependents":[395,394],"id":393,"thread":"build-66"},{"duration":12,"stepId":"io.quarkus.arc.deployment.LoggingBeanSupportProcessor#discoveredComponents","started":"15:28:33.598","dependents":[337,320,189],"id":119,"thread":"build-28"},{"duration":11,"stepId":"io.quarkus.container.image.openshift.deployment.OpenshiftProcessor#openshiftPrepareJvmDockerBuild","started":"15:28:33.624","dependents":[385],"id":171,"thread":"build-52"},{"duration":10,"stepId":"org.apache.camel.quarkus.core.deployment.CamelUnremovableBeansProcessor#buildTimeCamelCatalog","started":"15:28:34.282","dependents":[314,336],"id":310,"thread":"build-5"},{"duration":10,"stepId":"io.quarkus.deployment.dev.HotDeploymentWatchedFileBuildStep#setupWatchedFileHotDeployment","started":"15:28:33.660","dependents":[409,410],"id":223,"thread":"build-41"},{"duration":10,"stepId":"io.quarkus.container.image.deployment.devconsole.ContainerImageDevConsoleProcessor#builder","started":"15:28:33.595","dependents":[397,408],"id":87,"thread":"build-5"},{"duration":10,"stepId":"io.quarkus.vertx.http.deployment.devmode.console.ConfigEditorProcessor#config","started":"15:28:37.803","dependents":[409,413,395,397,408],"id":392,"thread":"build-39"},{"duration":10,"stepId":"org.apache.camel.quarkus.component.http.deployment.HttpProcessor#registerForReflection","started":"15:28:33.578","dependents":[412],"id":11,"thread":"build-4"},{"duration":9,"stepId":"io.quarkus.vertx.deployment.VertxProcessor#unremovableBeans","started":"15:28:33.600","dependents":[356,358],"id":117,"thread":"build-33"},{"duration":9,"stepId":"io.quarkus.kafka.client.deployment.KafkaProcessor#build","started":"15:28:34.282","dependents":[356,311,358,329,412],"id":309,"thread":"build-26"},{"duration":9,"stepId":"org.apache.camel.quarkus.core.deployment.main.CamelMainNativeImageProcessor#reflectiveCLasses","started":"15:28:33.593","dependents":[412],"id":68,"thread":"build-20"},{"duration":8,"stepId":"io.quarkus.kafka.client.deployment.KafkaProcessor#kafkaClientBeans","started":"15:28:33.584","dependents":[337,320],"id":21,"thread":"build-14"},{"duration":8,"stepId":"io.quarkus.arc.deployment.devconsole.ArcDevConsoleProcessor#collectBeanInfo","started":"15:28:34.483","dependents":[396,397,408],"id":365,"thread":"build-27"},{"duration":8,"stepId":"io.quarkus.vertx.http.deployment.VertxHttpProcessor#shouldNotRemoveHttpServerOptionsCustomizers","started":"15:28:33.602","dependents":[356,358],"id":133,"thread":"build-20"},{"duration":8,"stepId":"org.apache.camel.quarkus.core.deployment.CamelProcessor#unremovableBeans","started":"15:28:33.603","dependents":[337,320],"id":132,"thread":"build-39"},{"duration":8,"stepId":"io.quarkus.deployment.ide.IdeProcessor#detectIdeFiles","started":"15:28:33.596","dependents":[265],"id":78,"thread":"build-17"},{"duration":8,"stepId":"io.quarkus.deployment.steps.ThreadPoolSetup#createExecutor","started":"15:28:33.672","dependents":[404,413,245,374,246,250,249],"id":243,"thread":"build-10"},{"duration":8,"stepId":"org.apache.camel.quarkus.core.deployment.main.CamelMainHotDeploymentProcessor#locations","started":"15:28:33.592","dependents":[223],"id":58,"thread":"build-18"},{"duration":8,"stepId":"io.quarkus.vertx.http.deployment.VertxHttpProcessor#logging","started":"15:28:33.598","dependents":[102],"id":92,"thread":"build-13"},{"duration":7,"stepId":"io.quarkus.resteasy.deployment.ResteasyBuiltinsProcessor#vertxProviders","started":"15:28:33.594","dependents":[330],"id":63,"thread":"build-11"},{"duration":7,"stepId":"io.quarkus.vertx.core.deployment.VertxCoreProcessor#build_9d6b7122fb368970c50c3a870d1f672392cd8afb","started":"15:28:33.596","dependents":[311,329,412],"id":74,"thread":"build-16"},{"duration":7,"stepId":"io.quarkus.vertx.http.deployment.VertxHttpProcessor#cors","started":"15:28:33.666","dependents":[404,413],"id":229,"thread":"build-4"},{"duration":7,"stepId":"io.quarkus.resteasy.deployment.ResteasyBuiltinsProcessor#addStaticResourcesExceptionMapper","started":"15:28:34.278","dependents":[413],"id":308,"thread":"build-65"},{"duration":7,"stepId":"io.quarkus.vertx.core.deployment.VertxCoreProcessor#build_9fb3ce360263cc99d07c9172ec2feeaa85afcc1a","started":"15:28:33.680","dependents":[409,254,374,350,411,400,404,351,373,251,413,410,353,352],"id":250,"thread":"build-17"},{"duration":7,"stepId":"io.quarkus.vertx.http.deployment.devmode.BuildMetricsDevConsoleProcessor#collectMetrics","started":"15:28:33.578","dependents":[396],"id":8,"thread":"build-1"},{"duration":6,"stepId":"io.quarkus.kubernetes.deployment.OpenshiftProcessor#createConfigurators","started":"15:28:33.661","dependents":[385],"id":213,"thread":"build-5"},{"duration":6,"stepId":"io.quarkus.deployment.steps.ClassTransformingBuildStep#handleClassTransformation","started":"15:28:34.551","dependents":[],"id":376,"thread":"build-27"},{"duration":6,"stepId":"io.quarkus.deployment.logging.LoggingResourceProcessor#setupStackTraceFormatter","started":"15:28:34.278","dependents":[327],"id":305,"thread":"build-45"},{"duration":6,"stepId":"io.quarkus.arc.deployment.SyntheticBeansProcessor#initRegular","started":"15:28:34.455","dependents":[354],"id":353,"thread":"build-62"},{"duration":6,"stepId":"io.quarkus.vertx.core.deployment.VertxCoreProcessor#eventLoopCount","started":"15:28:33.667","dependents":[413,411],"id":228,"thread":"build-24"},{"duration":6,"stepId":"io.quarkus.jaxp.deployment.JaxpProcessor#resources","started":"15:28:33.587","dependents":[329],"id":31,"thread":"build-17"},{"duration":5,"stepId":"org.apache.camel.quarkus.core.deployment.CamelContextProcessor#context","started":"15:28:34.552","dependents":[381,413,379,383,380,378,402],"id":377,"thread":"build-25"},{"duration":5,"stepId":"io.quarkus.netty.deployment.NettyProcessor#cleanupUnsafeLog","started":"15:28:33.584","dependents":[145,327],"id":12,"thread":"build-13"},{"duration":5,"stepId":"org.apache.camel.quarkus.core.deployment.main.CamelMainProcessor#routesCollector","started":"15:28:33.677","dependents":[413,379],"id":247,"thread":"build-15"},{"duration":5,"stepId":"io.quarkus.vertx.http.deployment.VertxHttpProcessor#filterMultipleVertxInstancesWarning","started":"15:28:33.603","dependents":[145,327],"id":111,"thread":"build-18"},{"duration":5,"stepId":"io.quarkus.arc.deployment.StartupBuildSteps#addScope","started":"15:28:33.606","dependents":[326],"id":142,"thread":"build-46"},{"duration":5,"stepId":"io.quarkus.arc.deployment.SyntheticBeansProcessor#initRuntime","started":"15:28:34.456","dependents":[409,413,410,354,403],"id":352,"thread":"build-3"},{"duration":5,"stepId":"io.quarkus.vertx.http.deployment.devmode.console.DevConsoleProcessor#setupDevConsoleRoutes_0a9629c46f632dba90d4b3c7602ae4ea9d736452","started":"15:28:37.813","dependents":[413,398,408,400],"id":397,"thread":"build-50"},{"duration":5,"stepId":"io.quarkus.vertx.core.deployment.VertxCoreProcessor#doNotRemoveVertxOptionsCustomizers","started":"15:28:33.595","dependents":[356,358],"id":56,"thread":"build-19"},{"duration":5,"stepId":"io.quarkus.kubernetes.deployment.OpenshiftProcessor#checkOpenshift","started":"15:28:33.633","dependents":[261,199,260,180],"id":175,"thread":"build-61"},{"duration":4,"stepId":"io.quarkus.arc.deployment.ConfigBuildStep#additionalBeans","started":"15:28:33.609","dependents":[337,320],"id":150,"thread":"build-19"},{"duration":4,"stepId":"io.quarkus.netty.deployment.NettyProcessor#registerQualifiers","started":"15:28:33.600","dependents":[337,320],"id":75,"thread":"build-19"},{"duration":4,"stepId":"org.apache.camel.quarkus.core.deployment.main.CamelMainProcessor#unremovableBeans","started":"15:28:33.605","dependents":[337,320],"id":115,"thread":"build-16"},{"duration":4,"stepId":"io.quarkus.arc.deployment.ArcProcessor#registerSyntheticObservers","started":"15:28:34.462","dependents":[356,358,355,366,412],"id":354,"thread":"build-3"},{"duration":4,"stepId":"io.quarkus.vertx.deployment.VertxProcessor#featureAndCapability","started":"15:28:33.589","dependents":[163,413,291,380],"id":34,"thread":"build-19"},{"duration":4,"stepId":"io.quarkus.kubernetes.deployment.VanillaKubernetesProcessor#checkVanillaKubernetes","started":"15:28:33.633","dependents":[261,199,260,180],"id":174,"thread":"build-23"},{"duration":4,"stepId":"org.apache.camel.quarkus.component.jackson.JacksonProcessor#registerReflectiveClasses","started":"15:28:33.606","dependents":[412],"id":131,"thread":"build-34"},{"duration":4,"stepId":"io.quarkus.deployment.dev.testing.TestTracingProcessor#startTesting","started":"15:28:33.769","dependents":[409,410,327],"id":259,"thread":"build-57"},{"duration":4,"stepId":"io.quarkus.vertx.http.deployment.HttpSecurityProcessor#initBasicAuth","started":"15:28:33.670","dependents":[351,413,353,352],"id":231,"thread":"build-26"},{"duration":4,"stepId":"io.quarkus.openshift.deployment.OpenshiftDevConsoleProcessor#builder","started":"15:28:33.598","dependents":[397,408],"id":73,"thread":"build-14"},{"duration":4,"stepId":"io.quarkus.deployment.ExtensionLoader#config","started":"15:28:33.601","dependents":[248,164,110,182,206,247,191,270,250,109,190,330,138,253,377,219,309,183,413,403,175,406,256,157,177,376,411,243,292,370,112,168,397,174,324,285,222,306,134,323,231,113,327,390,265,349,143,124,121,232,130,135,144,140,229,258,404,332,328,384,278,199,189,387,272,149,254,301,218,374,146,181,139,286,391,237,400,410,141,198,196,147,211,221,170,208,358,151,312,407,383,260,364,213,171,262,179,366,178,214,153,379,261,169,156,372,357,160,154,373,252,268,255,337,259,228,320,176,385,155],"id":98,"thread":"build-31"},{"duration":4,"stepId":"io.quarkus.deployment.logging.LoggingResourceProcessor#setupLogFilters","started":"15:28:33.578","dependents":[145,327],"id":3,"thread":"build-3"},{"duration":4,"stepId":"org.apache.camel.quarkus.component.kafka.deployment.KafkaProcessor#configureKafkaComponentForDevServices","started":"15:28:37.803","dependents":[391],"id":390,"thread":"build-62"},{"duration":4,"stepId":"org.apache.camel.quarkus.core.deployment.main.CamelMainNativeImageProcessor#camelNativeImageResources","started":"15:28:33.633","dependents":[329],"id":173,"thread":"build-30"},{"duration":3,"stepId":"io.quarkus.arc.deployment.ConfigBuildStep#vetoMPConfigProperties","started":"15:28:33.590","dependents":[337],"id":29,"thread":"build-3"},{"duration":3,"stepId":"io.quarkus.smallrye.context.deployment.SmallRyeContextPropagationProcessor#build","started":"15:28:33.680","dependents":[351,413,353,352],"id":249,"thread":"build-3"},{"duration":3,"stepId":"io.quarkus.deployment.pkg.steps.JarResultBuildStep#outputTarget","started":"15:28:33.610","dependents":[171,261,199,386,260,385],"id":157,"thread":"build-56"},{"duration":3,"stepId":"io.quarkus.vertx.http.deployment.devmode.tests.TestsProcessor#runAllTests","started":"15:28:33.586","dependents":[397,408],"id":14,"thread":"build-3"},{"duration":3,"stepId":"io.quarkus.kafka.client.deployment.KafkaProcessor#runtimeConfig","started":"15:28:33.610","dependents":[337,320],"id":148,"thread":"build-43"},{"duration":3,"stepId":"io.quarkus.deployment.recording.substitutions.AdditionalSubstitutionsBuildStep#additionalSubstitutions","started":"15:28:33.602","dependents":[413],"id":88,"thread":"build-34"},{"duration":3,"stepId":"io.quarkus.vertx.http.deployment.HttpSecurityProcessor#initFormAuth","started":"15:28:33.666","dependents":[351,413,353,352,398,408,400],"id":218,"thread":"build-12"},{"duration":3,"stepId":"org.apache.camel.quarkus.core.deployment.InjectionPointsProcessor#annotationsTransformers","started":"15:28:33.587","dependents":[337],"id":16,"thread":"build-1"},{"duration":3,"stepId":"io.quarkus.vertx.http.deployment.devmode.tests.TestsProcessor#results","started":"15:28:33.581","dependents":[396],"id":7,"thread":"build-10"},{"duration":3,"stepId":"io.quarkus.vertx.http.deployment.devmode.console.DevConsoleProcessor#setupWebJar","started":"15:28:33.580","dependents":[262],"id":6,"thread":"build-9"},{"duration":3,"stepId":"org.apache.camel.quarkus.component.rest.deployment.RestProcessor#restFactories","started":"15:28:33.590","dependents":[328,318,383],"id":28,"thread":"build-11"},{"duration":3,"stepId":"org.apache.camel.quarkus.core.deployment.InjectionPointsProcessor#qualifierRegistrars","started":"15:28:33.601","dependents":[321,337],"id":79,"thread":"build-35"},{"duration":3,"stepId":"org.apache.camel.quarkus.core.deployment.CamelProcessor#discoverRoutesBuilderClassNames","started":"15:28:34.281","dependents":[379,307],"id":306,"thread":"build-16"},{"duration":2,"stepId":"io.quarkus.vertx.http.deployment.devmode.tests.TestsProcessor#toggleTestRunner","started":"15:28:33.595","dependents":[397,408],"id":46,"thread":"build-17"},{"duration":2,"stepId":"io.quarkus.arc.deployment.ArcProcessor#loggerProducer","started":"15:28:33.604","dependents":[337,320],"id":99,"thread":"build-40"},{"duration":2,"stepId":"io.quarkus.vertx.http.deployment.devmode.ArcDevProcessor#registerRoutes","started":"15:28:34.483","dependents":[413,398,408,399,366,400],"id":364,"thread":"build-45"},{"duration":2,"stepId":"io.quarkus.arc.deployment.HotDeploymentConfigBuildStep#startup","started":"15:28:33.602","dependents":[96],"id":80,"thread":"build-30"},{"duration":2,"stepId":"io.quarkus.arc.deployment.ArcProcessor#marker","started":"15:28:33.606","dependents":[268],"id":114,"thread":"build-19"},{"duration":2,"stepId":"org.apache.camel.quarkus.component.platform.http.deployment.PlatformHttpProcessor#serviceFilter","started":"15:28:33.607","dependents":[383],"id":108,"thread":"build-48"},{"duration":2,"stepId":"io.quarkus.deployment.steps.CombinedIndexBuildStep#build","started":"15:28:34.278","dependents":[289,315,276,275,277,362,332,274,300,278,380,341,335,330,299,301,313,303,296,287,374,286,309,288,339,279,297,403,280,293,281,291,316,292,302,347,325,295,298,282,283,284,285,306,327,310,290,337,304],"id":273,"thread":"build-62"},{"duration":2,"stepId":"io.quarkus.deployment.dev.IsolatedDevModeMain$5$1@4fd60ae4","started":"15:28:33.598","dependents":[337],"id":60,"thread":"build-30"},{"duration":2,"stepId":"io.quarkus.deployment.steps.CapabilityAggregationStep#provideCapabilities","started":"15:28:33.612","dependents":[163,291,380],"id":152,"thread":"build-61"},{"duration":2,"stepId":"io.quarkus.vertx.http.deployment.devmode.tests.TestsProcessor#forceRestart","started":"15:28:33.602","dependents":[397,408],"id":77,"thread":"build-11"},{"duration":2,"stepId":"io.quarkus.resteasy.deployment.ResteasyBuiltinsProcessor#setUpSecurity","started":"15:28:33.633","dependents":[330,337,320],"id":172,"thread":"build-56"},{"duration":2,"stepId":"io.quarkus.kubernetes.deployment.KnativeProcessor#createAnnotations","started":"15:28:33.609","dependents":[261,199,260],"id":138,"thread":"build-49"},{"duration":2,"stepId":"io.quarkus.vertx.deployment.VertxProcessor#registerBean","started":"15:28:33.609","dependents":[337,320],"id":136,"thread":"build-53"},{"duration":2,"stepId":"io.quarkus.arc.deployment.staticmethods.InterceptedStaticMethodsProcessor#collectInterceptedStaticMethods","started":"15:28:34.453","dependents":[356,358,369,346],"id":345,"thread":"build-62"},{"duration":2,"stepId":"io.quarkus.deployment.steps.BlockingOperationControlBuildStep#blockingOP","started":"15:28:33.671","dependents":[413],"id":230,"thread":"build-41"},{"duration":2,"stepId":"org.apache.camel.quarkus.core.deployment.CamelProcessor#containerBeans","started":"15:28:34.453","dependents":[379,383,354,402],"id":348,"thread":"build-59"},{"duration":2,"stepId":"io.quarkus.vertx.http.deployment.devmode.tests.TestsProcessor#printfailures","started":"15:28:33.588","dependents":[397,408],"id":18,"thread":"build-18"},{"duration":2,"stepId":"io.quarkus.netty.deployment.NettyProcessor#build","started":"15:28:33.612","dependents":[311,412],"id":151,"thread":"build-53"},{"duration":2,"stepId":"org.apache.camel.quarkus.core.deployment.CamelProcessor#componentNameResolver","started":"15:28:34.293","dependents":[413,377],"id":314,"thread":"build-26"},{"duration":2,"stepId":"io.quarkus.vertx.http.deployment.VertxHttpProcessor#httpRoot","started":"15:28:33.611","dependents":[404,333,192,217,202,372,399],"id":149,"thread":"build-20"},{"duration":2,"stepId":"io.quarkus.resteasy.common.deployment.ResteasyCommonProcessor#disableDefaultExceptionMapper","started":"15:28:33.606","dependents":[413],"id":110,"thread":"build-17"},{"duration":2,"stepId":"io.quarkus.deployment.steps.RegisterForReflectionBuildStep#build","started":"15:28:34.282","dependents":[335,412],"id":303,"thread":"build-7"},{"duration":2,"stepId":"io.quarkus.vertx.http.deployment.VertxHttpProcessor#finalizeRouter","started":"15:28:37.819","dependents":[409,413,410,406],"id":404,"thread":"build-50"},{"duration":2,"stepId":"io.quarkus.vertx.http.deployment.devmode.tests.TestsProcessor#toggleInstrumentation","started":"15:28:33.588","dependents":[397,408],"id":17,"thread":"build-16"},{"duration":2,"stepId":"io.quarkus.arc.deployment.ArcProcessor#launchMode","started":"15:28:33.587","dependents":[337,320],"id":13,"thread":"build-11"},{"duration":2,"stepId":"io.quarkus.jackson.deployment.JacksonProcessor#jacksonSupport","started":"15:28:34.282","dependents":[351,413,353,352],"id":301,"thread":"build-22"},{"duration":2,"stepId":"io.quarkus.kubernetes.deployment.KubernetesProcessor#enabledKubernetesDeploymentTargets","started":"15:28:33.638","dependents":[385],"id":180,"thread":"build-61"},{"duration":2,"stepId":"org.apache.camel.quarkus.core.deployment.InjectionPointsProcessor#injectedComponents","started":"15:28:34.453","dependents":[351,413,353,352,354,403],"id":347,"thread":"build-57"},{"duration":2,"stepId":"io.quarkus.netty.deployment.NettyProcessor#cleanupMacDNSInLog","started":"15:28:33.606","dependents":[145,327],"id":107,"thread":"build-43"},{"duration":2,"stepId":"io.quarkus.kafka.client.deployment.KafkaProcessor#withSasl","started":"15:28:34.281","dependents":[311,412],"id":300,"thread":"build-55"},{"duration":2,"stepId":"io.quarkus.vertx.http.deployment.devmode.tests.TestsProcessor#handleTestStatus","started":"15:28:33.590","dependents":[397,408],"id":24,"thread":"build-20"},{"duration":1,"stepId":"io.quarkus.vertx.deployment.VertxProcessor#registerVerticleClasses","started":"15:28:34.282","dependents":[412],"id":299,"thread":"build-10"},{"duration":1,"stepId":"org.apache.camel.quarkus.core.deployment.CamelContextProcessor#registerCamelEventBridges","started":"15:28:34.558","dependents":[413],"id":381,"thread":"build-27"},{"duration":1,"stepId":"io.quarkus.vertx.http.deployment.devmode.tests.TestsProcessor#runFailedTests","started":"15:28:33.607","dependents":[397,408],"id":105,"thread":"build-35"},{"duration":1,"stepId":"io.quarkus.deployment.steps.ProfileBuildStep#defaultProfile","started":"15:28:33.589","dependents":[391],"id":20,"thread":"build-5"},{"duration":1,"stepId":"io.quarkus.deployment.CollectionClassProcessor#setupCollectionClasses","started":"15:28:33.609","dependents":[412],"id":122,"thread":"build-17"},{"duration":1,"stepId":"io.quarkus.smallrye.context.deployment.SmallRyeContextPropagationProcessor#registerBean","started":"15:28:33.601","dependents":[337,320],"id":69,"thread":"build-18"},{"duration":1,"stepId":"io.quarkus.container.image.deployment.devconsole.ContainerImageDevConsoleProcessor#handleGetBuilders","started":"15:28:33.599","dependents":[396],"id":62,"thread":"build-27"},{"duration":1,"stepId":"io.quarkus.resteasy.server.common.deployment.ResteasyServerCommonProcessor#build","started":"15:28:34.349","dependents":[371,333,356,358,337,376,335,372,412],"id":332,"thread":"build-62"},{"duration":1,"stepId":"io.quarkus.vertx.http.deployment.VertxHttpProcessor#hostDefault","started":"15:28:33.600","dependents":[200],"id":65,"thread":"build-25"},{"duration":1,"stepId":"io.quarkus.deployment.logging.LoggingResourceProcessor#setUpDarkeningDefault","started":"15:28:33.601","dependents":[391],"id":72,"thread":"build-27"},{"duration":1,"stepId":"io.quarkus.kubernetes.deployment.VanillaKubernetesProcessor#createLabels","started":"15:28:33.612","dependents":[261,199,260],"id":153,"thread":"build-58"},{"duration":1,"stepId":"io.quarkus.jackson.deployment.JacksonProcessor#generateCustomizer","started":"15:28:34.283","dependents":[320],"id":304,"thread":"build-62"},{"duration":1,"stepId":"io.quarkus.deployment.dev.testing.TestTracingProcessor#sharedStateListener","started":"15:28:33.593","dependents":[259],"id":32,"thread":"build-13"},{"duration":1,"stepId":"io.quarkus.mutiny.deployment.MutinyProcessor#runtimeInit","started":"15:28:33.680","dependents":[413],"id":246,"thread":"build-35"},{"duration":1,"stepId":"io.quarkus.arc.deployment.ArcProcessor#registerContextPropagation","started":"15:28:33.611","dependents":[240],"id":146,"thread":"build-57"},{"duration":1,"stepId":"io.quarkus.arc.deployment.BuildTimeEnabledProcessor#ifBuildProperty","started":"15:28:34.281","dependents":[294,332],"id":289,"thread":"build-17"},{"duration":1,"stepId":"io.quarkus.arc.deployment.ArcProcessor#unremovableAsyncObserverExceptionHandlers","started":"15:28:33.597","dependents":[356,358],"id":53,"thread":"build-27"},{"duration":1,"stepId":"io.quarkus.arc.deployment.AutoAddScopeProcessor#annotationTransformer","started":"15:28:34.309","dependents":[356,358,337],"id":326,"thread":"build-7"},{"duration":1,"stepId":"org.apache.camel.quarkus.component.platform.http.deployment.PlatformHttpProcessor#platformHttpEngineBean","started":"15:28:33.665","dependents":[402],"id":212,"thread":"build-46"},{"duration":1,"stepId":"io.quarkus.arc.deployment.StartupBuildSteps#unremovableBeans","started":"15:28:33.596","dependents":[356,358],"id":47,"thread":"build-13"},{"duration":1,"stepId":"io.quarkus.vertx.core.deployment.VertxCoreProcessor#overrideContextInternalInterfaceToAddSafeGuards","started":"15:28:33.596","dependents":[376],"id":48,"thread":"build-25"},{"duration":1,"stepId":"org.apache.camel.quarkus.core.deployment.CamelUnremovableBeansProcessor#unremovableOptionalServices","started":"15:28:34.283","dependents":[356,358],"id":302,"thread":"build-19"},{"duration":1,"stepId":"io.quarkus.vertx.http.deployment.StaticResourcesProcessor#runtimeInit","started":"15:28:34.552","dependents":[404,413],"id":373,"thread":"build-59"},{"duration":1,"stepId":"org.apache.camel.quarkus.component.jackson.JacksonProcessor#feature","started":"15:28:33.578","dependents":[413],"id":1,"thread":"build-5"},{"duration":1,"stepId":"org.apache.camel.quarkus.component.kafka.deployment.KafkaProcessor#reflectiveClasses","started":"15:28:34.282","dependents":[412],"id":297,"thread":"build-24"},{"duration":1,"stepId":"io.quarkus.arc.deployment.SyntheticBeansProcessor#initStatic","started":"15:28:34.455","dependents":[413,354],"id":351,"thread":"build-51"},{"duration":1,"stepId":"io.quarkus.jackson.deployment.JacksonProcessor#register","started":"15:28:34.281","dependents":[337,335,320,412],"id":296,"thread":"build-50"},{"duration":1,"stepId":"io.quarkus.jackson.deployment.JacksonProcessor#supportMixins","started":"15:28:34.282","dependents":[351,413,353,352,412],"id":295,"thread":"build-12"},{"duration":1,"stepId":"io.quarkus.arc.deployment.ConfigBuildStep#registerConfigClasses","started":"15:28:34.483","dependents":[413],"id":363,"thread":"build-59"},{"duration":1,"stepId":"io.quarkus.smallrye.context.deployment.SmallRyeContextPropagationProcessor#transformInjectionPoint","started":"15:28:33.596","dependents":[337],"id":49,"thread":"build-14"},{"duration":1,"stepId":"org.apache.camel.quarkus.core.deployment.CamelProcessor#unremovableRoutesBuilders","started":"15:28:33.579","dependents":[356,358],"id":2,"thread":"build-7"},{"duration":1,"stepId":"io.quarkus.vertx.http.deployment.devmode.console.DevConsoleProcessor#setupDevConsoleRoutes_8bb86a3e770caadb970f4facb490e30df7a2a187","started":"15:28:33.862","dependents":[413,398,408,400],"id":263,"thread":"build-18"},{"duration":1,"stepId":"io.quarkus.deployment.steps.ReflectiveHierarchyStep#build","started":"15:28:34.350","dependents":[412],"id":335,"thread":"build-18"},{"duration":1,"stepId":"io.quarkus.arc.deployment.WrongAnnotationUsageProcessor#detect","started":"15:28:34.454","dependents":[366],"id":349,"thread":"build-27"},{"duration":1,"stepId":"io.quarkus.kafka.client.deployment.KafkaProcessor#setupWebJar","started":"15:28:33.599","dependents":[64,263],"id":61,"thread":"build-31"},{"duration":1,"stepId":"io.quarkus.deployment.steps.NativeImageConfigBuildStep#build","started":"15:28:34.291","dependents":[413],"id":311,"thread":"build-65"},{"duration":1,"stepId":"io.quarkus.kubernetes.deployment.OpenshiftProcessor#createAnnotations","started":"15:28:33.612","dependents":[261,199,260],"id":147,"thread":"build-55"},{"duration":1,"stepId":"io.quarkus.vertx.http.deployment.devmode.tests.TestsProcessor#toggleTestOutput","started":"15:28:33.609","dependents":[397,408],"id":123,"thread":"build-51"},{"duration":1,"stepId":"io.quarkus.arc.deployment.ArcProcessor#transformListAllInjectionPoints","started":"15:28:33.607","dependents":[337],"id":106,"thread":"build-47"},{"duration":1,"stepId":"io.quarkus.deployment.pkg.steps.PackageTypeVerificationBuildStep#verify","started":"15:28:33.613","dependents":[409,410],"id":156,"thread":"build-52"},{"duration":1,"stepId":"org.apache.camel.quarkus.component.http.deployment.HttpProcessor#activateSslNativeSupport","started":"15:28:33.591","dependents":[311],"id":22,"thread":"build-4"},{"duration":1,"stepId":"io.quarkus.openshift.deployment.OpenshiftProcessor#checkOpenshift","started":"15:28:33.633","dependents":[261,199,260,180],"id":170,"thread":"build-31"},{"duration":1,"stepId":"io.quarkus.vertx.http.deployment.devmode.console.ConfigEditorProcessor#handleRequests","started":"15:28:37.803","dependents":[397,408],"id":389,"thread":"build-50"},{"duration":1,"stepId":"io.quarkus.deployment.logging.LoggingResourceProcessor#setUpDefaultLogCleanupFilters","started":"15:28:33.611","dependents":[391],"id":145,"thread":"build-17"},{"duration":1,"stepId":"io.quarkus.arc.deployment.ArcProcessor#convertLegacyAdditionalStereotypes","started":"15:28:33.593","dependents":[337,323],"id":36,"thread":"build-14"},{"duration":1,"stepId":"io.quarkus.vertx.http.deployment.devmode.tests.TestsProcessor#toggleLiveReloadEnabled","started":"15:28:33.600","dependents":[397,408],"id":67,"thread":"build-30"},{"duration":1,"stepId":"org.apache.camel.quarkus.core.deployment.ConsumeProcessor#annotationsTransformers","started":"15:28:33.595","dependents":[337],"id":44,"thread":"build-25"},{"duration":1,"stepId":"io.quarkus.kafka.client.deployment.KafkaProcessor#ensureJsonParserAvailable","started":"15:28:33.591","dependents":[356,358],"id":25,"thread":"build-1"},{"duration":1,"stepId":"io.quarkus.resteasy.common.deployment.ResteasyCommonProcessor#setupResteasyInjection","started":"15:28:34.552","dependents":[371,413,372],"id":370,"thread":"build-50"},{"duration":0,"stepId":"io.quarkus.arc.deployment.BuildTimeEnabledProcessor#unlessBuildProperty","started":"15:28:34.282","dependents":[294,332],"id":290,"thread":"build-46"},{"duration":0,"stepId":"org.apache.camel.quarkus.core.deployment.main.CamelMainProcessor#main","started":"15:28:34.558","dependents":[413,382,403],"id":379,"thread":"build-17"},{"duration":0,"stepId":"io.quarkus.deployment.steps.NativeImageResourcesStep#registerPackageResources","started":"15:28:33.599","dependents":[329],"id":55,"thread":"build-27"},{"duration":0,"stepId":"io.quarkus.deployment.JniProcessor#setupJni","started":"15:28:33.611","dependents":[311],"id":139,"thread":"build-55"},{"duration":0,"stepId":"org.apache.camel.quarkus.core.deployment.ConsumeProcessor#unremovables","started":"15:28:34.281","dependents":[356,358,412],"id":274,"thread":"build-35"},{"duration":0,"stepId":"io.quarkus.deployment.steps.ConfigGenerationBuildStep#runtimeDefaultsConfig","started":"15:28:37.807","dependents":[407,412],"id":391,"thread":"build-50"},{"duration":0,"stepId":"org.apache.camel.quarkus.core.deployment.CamelSerializationProcessor#baseSerializationClasses","started":"15:28:33.625","dependents":[412],"id":159,"thread":"build-63"},{"duration":0,"stepId":"io.quarkus.deployment.console.ConsoleProcessor#installCliCommands","started":"15:28:37.816","dependents":[409,410],"id":395,"thread":"build-39"},{"duration":0,"stepId":"io.quarkus.vertx.core.deployment.VertxCoreProcessor#cleanupVertxWarnings","started":"15:28:33.605","dependents":[145,327],"id":86,"thread":"build-17"},{"duration":0,"stepId":"io.quarkus.resteasy.deployment.ResteasyServletProcessor#webXmlMapping","started":"15:28:33.604","dependents":[332],"id":81,"thread":"build-35"},{"duration":0,"stepId":"org.apache.camel.quarkus.core.cloud.deployment.CloudProcessor#servicePatterns","started":"15:28:33.595","dependents":[328,318,383],"id":40,"thread":"build-13"},{"duration":0,"stepId":"io.quarkus.deployment.console.ConsoleProcessor#setupExceptionHandler","started":"15:28:33.871","dependents":[305],"id":267,"thread":"build-27"},{"duration":0,"stepId":"io.quarkus.deployment.steps.NativeImageFeatureStep#generateNativeResourcesList","started":"15:28:34.328","dependents":[],"id":329,"thread":"build-62"},{"duration":0,"stepId":"org.apache.camel.quarkus.core.deployment.main.CamelMainProcessor#registerCamelMainEventBridge","started":"15:28:34.559","dependents":[413],"id":382,"thread":"build-62"},{"duration":0,"stepId":"io.quarkus.deployment.steps.CurateOutcomeBuildStep#removeResources","started":"15:28:33.614","dependents":[376],"id":155,"thread":"build-59"},{"duration":0,"stepId":"io.quarkus.arc.deployment.ConfigBuildStep#validateConfigMappingsInjectionPoints","started":"15:28:34.483","dependents":[407,363],"id":358,"thread":"build-59"},{"duration":0,"stepId":"io.quarkus.arc.deployment.ConfigBuildStep#registerConfigMappingConverters","started":"15:28:34.282","dependents":[412],"id":293,"thread":"build-44"},{"duration":0,"stepId":"org.apache.camel.quarkus.component.kafka.deployment.KafkaProcessor#feature","started":"15:28:33.585","dependents":[413],"id":9,"thread":"build-16"},{"duration":0,"stepId":"io.quarkus.deployment.ide.IdeProcessor#effectiveIde","started":"15:28:33.871","dependents":[267,408,305,266],"id":265,"thread":"build-18"},{"duration":0,"stepId":"io.quarkus.deployment.steps.AdditionalClassLoaderResourcesBuildStep#appendAdditionalClassloaderResources","started":"15:28:33.583","dependents":[273],"id":5,"thread":"build-12"},{"duration":0,"stepId":"io.quarkus.resteasy.jackson.deployment.ResteasyJacksonProcessor#feature","started":"15:28:33.605","dependents":[413],"id":89,"thread":"build-19"},{"duration":0,"stepId":"io.quarkus.deployment.index.ApplicationArchiveBuildStep#addConfiguredIndexedDependencies","started":"15:28:33.610","dependents":[268],"id":121,"thread":"build-6"},{"duration":0,"stepId":"org.apache.camel.quarkus.core.deployment.CamelNativeImageProcessor#camelServices","started":"15:28:34.307","dependents":[412],"id":319,"thread":"build-18"},{"duration":0,"stepId":"io.quarkus.arc.deployment.ArcProcessor#quarkusApplication","started":"15:28:34.282","dependents":[337,320],"id":287,"thread":"build-58"},{"duration":0,"stepId":"org.apache.camel.quarkus.core.deployment.CamelNativeImageProcessor#reflection","started":"15:28:34.278","dependents":[412],"id":272,"thread":"build-17"},{"duration":0,"stepId":"io.quarkus.deployment.logging.LoggingResourceProcessor#setProperty","started":"15:28:33.606","dependents":[413],"id":94,"thread":"build-35"},{"duration":0,"stepId":"io.quarkus.arc.deployment.AutoInjectFieldProcessor#autoInjectQualifiers","started":"15:28:34.308","dependents":[332,326,324],"id":321,"thread":"build-3"},{"duration":0,"stepId":"io.quarkus.resteasy.deployment.ResteasyStandaloneBuildStep#boot","started":"15:28:34.554","dependents":[404,413,398,408,400],"id":374,"thread":"build-17"},{"duration":0,"stepId":"io.quarkus.resteasy.server.common.deployment.ResteasyServerCommonProcessor#processPathInterfaceImplementors","started":"15:28:34.283","dependents":[356,358,337,320],"id":292,"thread":"build-11"},{"duration":0,"stepId":"io.quarkus.deployment.logging.LoggingWithPanacheProcessor#process","started":"15:28:34.281","dependents":[376],"id":275,"thread":"build-16"},{"duration":0,"stepId":"io.quarkus.undertow.deployment.UndertowStaticResourcesBuildStep#nativeImageResources","started":"15:28:34.278","dependents":[329],"id":271,"thread":"build-3"},{"duration":0,"stepId":"io.quarkus.vertx.http.deployment.devmode.console.DevConsoleProcessor#config","started":"15:28:37.816","dependents":[396],"id":394,"thread":"build-7"},{"duration":0,"stepId":"io.quarkus.vertx.http.deployment.devmode.console.DevConsoleProcessor#runtimeTemplates","started":"15:28:38.430","dependents":[413],"id":409,"thread":"build-62"},{"duration":0,"stepId":"io.quarkus.resteasy.server.common.deployment.ResteasyLogFilterBuildStep#setupLogFilters","started":"15:28:33.611","dependents":[145,327],"id":127,"thread":"build-55"},{"duration":0,"stepId":"org.apache.camel.quarkus.component.json.path.deployment.JsonPathProcessor#feature","started":"15:28:33.582","dependents":[413],"id":4,"thread":"build-11"},{"duration":0,"stepId":"io.quarkus.container.image.deployment.ContainerImageProcessor#ignoreCredentialsChange","started":"15:28:33.593","dependents":[248],"id":30,"thread":"build-4"},{"duration":0,"stepId":"io.quarkus.resteasy.deployment.RestPathAnnotationProcessor#findRestPaths","started":"15:28:34.350","dependents":[337],"id":334,"thread":"build-62"},{"duration":0,"stepId":"io.quarkus.arc.deployment.ConfigBuildStep#validateConfigInjectionPoints","started":"15:28:34.483","dependents":[368],"id":359,"thread":"build-62"},{"duration":0,"stepId":"io.quarkus.vertx.core.deployment.VertxCoreProcessor#preventLoggerContention","started":"15:28:33.594","dependents":[102],"id":35,"thread":"build-24"},{"duration":0,"stepId":"io.quarkus.deployment.ForkJoinPoolProcessor#setProperty","started":"15:28:33.611","dependents":[413],"id":129,"thread":"build-52"},{"duration":0,"stepId":"io.quarkus.vertx.http.deployment.devmode.tests.TestsProcessor#handleTestResult","started":"15:28:33.594","dependents":[397,408],"id":37,"thread":"build-5"},{"duration":0,"stepId":"io.quarkus.kubernetes.deployment.devconsole.KubernetesDevConsoleProcessor#builder","started":"15:28:33.605","dependents":[396],"id":84,"thread":"build-42"},{"duration":0,"stepId":"org.apache.camel.quarkus.component.bean.deployment.BeanProcessor#feature","started":"15:28:33.593","dependents":[413],"id":27,"thread":"build-1"},{"duration":0,"stepId":"io.quarkus.deployment.steps.DevServicesConfigBuildStep#setup","started":"15:28:37.802","dependents":[409,410,392,393,389,391,390],"id":388,"thread":"build-7"},{"duration":0,"stepId":"io.quarkus.arc.deployment.ConfigBuildStep#warnStaticInitInjectionPoints","started":"15:28:34.483","dependents":[391],"id":362,"thread":"build-51"},{"duration":0,"stepId":"io.quarkus.arc.deployment.BuildTimeEnabledProcessor#unlessBuildProfile","started":"15:28:34.282","dependents":[294,332],"id":283,"thread":"build-8"},{"duration":0,"stepId":"org.apache.camel.quarkus.core.deployment.CamelBootstrapProcessor#boot","started":"15:28:37.821","dependents":[409,413,410],"id":405,"thread":"build-7"},{"duration":0,"stepId":"org.apache.camel.quarkus.core.deployment.CamelSerializationProcessor#produceSerializationBuildItem","started":"15:28:33.611","dependents":[159],"id":135,"thread":"build-61"},{"duration":0,"stepId":"io.quarkus.kafka.client.deployment.KafkaProcessor#contributeClassesToIndex","started":"15:28:33.605","dependents":[268,273],"id":90,"thread":"build-46"},{"duration":0,"stepId":"io.quarkus.arc.deployment.AutoProducerMethodsProcessor#annotationTransformer","started":"15:28:34.308","dependents":[337],"id":323,"thread":"build-26"},{"duration":0,"stepId":"org.apache.camel.quarkus.component.attachments.deployment.AttachmentsProcessor#feature","started":"15:28:33.596","dependents":[413],"id":45,"thread":"build-3"},{"duration":0,"stepId":"io.quarkus.kubernetes.deployment.VanillaKubernetesProcessor#createAnnotations","started":"15:28:33.611","dependents":[261,199,260],"id":140,"thread":"build-16"},{"duration":0,"stepId":"io.quarkus.vertx.http.deployment.HttpSecurityProcessor#initMtlsClientAuth","started":"15:28:33.670","dependents":[351,413,353,352],"id":221,"thread":"build-59"},{"duration":0,"stepId":"io.quarkus.deployment.steps.RuntimeConfigSetupBuildStep#setupRuntimeConfig","started":"15:28:33.665","dependents":[248,254,253,218,231,374,411,327,243,229,400,404,373,413,252,410,228,250,406,221],"id":207,"thread":"build-38"},{"duration":0,"stepId":"org.apache.camel.quarkus.component.bean.deployment.BeanProcessor#registerReflectiveClasses","started":"15:28:34.283","dependents":[412],"id":298,"thread":"build-43"},{"duration":0,"stepId":"io.quarkus.resteasy.deployment.ResteasyStandaloneBuildStep#staticInit","started":"15:28:34.553","dependents":[413,374],"id":372,"thread":"build-62"},{"duration":0,"stepId":"io.quarkus.arc.deployment.ArcProcessor#feature","started":"15:28:33.605","dependents":[413],"id":83,"thread":"build-41"},{"duration":0,"stepId":"io.quarkus.deployment.recording.AnnotationProxyBuildStep#build","started":"15:28:33.723","dependents":[350],"id":257,"thread":"build-57"},{"duration":0,"stepId":"io.quarkus.vertx.core.deployment.VertxCoreProcessor#registerVerticleClasses","started":"15:28:34.282","dependents":[412],"id":288,"thread":"build-41"},{"duration":0,"stepId":"org.apache.camel.quarkus.core.deployment.CamelProcessor#initResources","started":"15:28:33.592","dependents":[329],"id":23,"thread":"build-16"},{"duration":0,"stepId":"io.quarkus.arc.deployment.LookupConditionsProcessor#suppressConditionsGenerators","started":"15:28:34.308","dependents":[337],"id":322,"thread":"build-51"},{"duration":0,"stepId":"org.apache.camel.quarkus.core.deployment.main.CamelMainProcessor#runtime","started":"15:28:37.820","dependents":[413,405],"id":403,"thread":"build-66"},{"duration":0,"stepId":"io.quarkus.resteasy.deployment.ResteasyBuiltinsProcessor#addAdditionalEndpointsExceptionMapper","started":"15:28:37.818","dependents":[413],"id":399,"thread":"build-50"},{"duration":0,"stepId":"io.quarkus.resteasy.deployment.ResteasyServletProcessor#jaxrsConfig","started":"15:28:34.350","dependents":[334],"id":333,"thread":"build-59"},{"duration":0,"stepId":"io.quarkus.deployment.steps.MainClassBuildStep#mainClassBuildStep","started":"15:28:34.281","dependents":[],"id":286,"thread":"build-28"},{"duration":0,"stepId":"io.quarkus.arc.deployment.LifecycleEventsBuildStep#startupEvent","started":"15:28:38.430","dependents":[413,411],"id":410,"thread":"build-66"},{"duration":0,"stepId":"org.apache.camel.quarkus.core.deployment.CamelNativeImageProcessor#reflectiveRoutes","started":"15:28:34.285","dependents":[412],"id":307,"thread":"build-45"},{"duration":0,"stepId":"io.quarkus.kafka.client.deployment.KafkaProcessor#feature","started":"15:28:33.609","dependents":[413],"id":116,"thread":"build-48"},{"duration":0,"stepId":"io.quarkus.jackson.deployment.JacksonProcessor#unremovable","started":"15:28:34.282","dependents":[356,358],"id":280,"thread":"build-1"},{"duration":0,"stepId":"io.quarkus.deployment.ConstructorPropertiesProcessor#build","started":"15:28:34.282","dependents":[412],"id":281,"thread":"build-32"},{"duration":0,"stepId":"io.quarkus.resteasy.server.common.deployment.ResteasyServerCommonProcessor#registerCompatibleAnnotationPrefixes","started":"15:28:33.614","dependents":[332],"id":154,"thread":"build-20"},{"duration":0,"stepId":"io.quarkus.resteasy.common.deployment.ResteasyCommonProcessor#resteasyConfig","started":"15:28:33.633","dependents":[330],"id":169,"thread":"build-20"},{"duration":0,"stepId":"io.quarkus.kubernetes.deployment.KnativeProcessor#createDecorators","started":"15:28:33.661","dependents":[385],"id":199,"thread":"build-4"},{"duration":0,"stepId":"io.quarkus.arc.deployment.ArcProcessor#setupExecutor","started":"15:28:33.680","dependents":[413],"id":245,"thread":"build-55"},{"duration":0,"stepId":"io.quarkus.kubernetes.deployment.OpenshiftProcessor#populateInternalRegistry","started":"15:28:33.633","dependents":[261,196],"id":168,"thread":"build-63"},{"duration":0,"stepId":"io.quarkus.deployment.ExtensionLoader#booleanSupplierFactory","started":"15:28:33.606","dependents":[152],"id":97,"thread":"build-17"},{"duration":0,"stepId":"io.quarkus.netty.deployment.NettyProcessor#registerEventLoopBeans","started":"15:28:33.687","dependents":[351,413,353,352],"id":251,"thread":"build-45"},{"duration":0,"stepId":"io.quarkus.vertx.http.deployment.VertxHttpProcessor#kubernetes","started":"15:28:33.592","dependents":[261,199,191,260,190,213,385],"id":26,"thread":"build-5"},{"duration":0,"stepId":"io.quarkus.vertx.http.deployment.devmode.console.DevConsoleProcessor#buildTimeTemplates","started":"15:28:37.816","dependents":[409,410],"id":396,"thread":"build-66"},{"duration":0,"stepId":"org.apache.camel.quarkus.component.platform.http.deployment.PlatformHttpProcessor#feature","started":"15:28:33.607","dependents":[413],"id":103,"thread":"build-49"},{"duration":0,"stepId":"io.quarkus.vertx.http.deployment.VertxHttpProcessor#initializeRouter","started":"15:28:37.818","dependents":[404,401,413],"id":400,"thread":"build-7"},{"duration":0,"stepId":"io.quarkus.deployment.steps.DevServicesConfigBuildStep#deprecated","started":"15:28:33.599","dependents":[388],"id":59,"thread":"build-32"},{"duration":0,"stepId":"io.quarkus.jaxp.deployment.JaxpProcessor#reflectiveClasses","started":"15:28:33.611","dependents":[412],"id":125,"thread":"build-51"},{"duration":0,"stepId":"org.apache.camel.quarkus.support.httpclient.deployment.HttpClientProcessor#markers","started":"15:28:33.595","dependents":[268],"id":39,"thread":"build-24"},{"duration":0,"stepId":"io.quarkus.vertx.http.deployment.devmode.console.DevConsoleProcessor#builder","started":"15:28:33.871","dependents":[397,408],"id":266,"thread":"build-16"},{"duration":0,"stepId":"io.quarkus.deployment.steps.ReflectiveHierarchyStep#ignoreJavaClassWarnings","started":"15:28:33.610","dependents":[335],"id":137,"thread":"build-48"},{"duration":0,"stepId":"io.quarkus.deployment.steps.ConfigGenerationBuildStep#suppressNonRuntimeConfigChanged","started":"15:28:33.605","dependents":[248],"id":91,"thread":"build-35"},{"duration":0,"stepId":"io.quarkus.kafka.client.deployment.KafkaProcessor#relaxSaslElytron","started":"15:28:33.590","dependents":[391],"id":19,"thread":"build-13"},{"duration":0,"stepId":"io.quarkus.deployment.steps.ConfigGenerationBuildStep#staticInitSources","started":"15:28:33.607","dependents":[407],"id":104,"thread":"build-13"},{"duration":0,"stepId":"io.quarkus.kafka.client.deployment.KafkaProcessor#logging","started":"15:28:33.595","dependents":[102],"id":41,"thread":"build-3"},{"duration":0,"stepId":"org.apache.camel.quarkus.core.deployment.InjectionPointsProcessor#syntheticBeans","started":"15:28:34.282","dependents":[351,413,353,352],"id":291,"thread":"build-47"},{"duration":0,"stepId":"io.quarkus.arc.deployment.devconsole.ArcDevConsoleProcessor#monitor","started":"15:28:33.651","dependents":[409,337,320],"id":189,"thread":"build-29"},{"duration":0,"stepId":"io.quarkus.undertow.deployment.UndertowStaticResourcesBuildStep#scanStaticResources","started":"15:28:34.278","dependents":[271],"id":269,"thread":"build-16"},{"duration":0,"stepId":"io.quarkus.resteasy.common.deployment.ResteasyCommonProcessor#addStaticInitConfigSourceProvider","started":"15:28:33.633","dependents":[407,412],"id":164,"thread":"build-6"},{"duration":0,"stepId":"io.quarkus.arc.deployment.UnremovableAnnotationsProcessor#unremovableBeans","started":"15:28:33.606","dependents":[356,358],"id":100,"thread":"build-13"},{"duration":0,"stepId":"io.quarkus.resteasy.server.common.deployment.ResteasyServerCommonProcessor#beanDefiningAnnotations","started":"15:28:33.612","dependents":[337,320,189],"id":144,"thread":"build-59"},{"duration":0,"stepId":"io.quarkus.resteasy.common.deployment.ResteasyCommonProcessor#configInjectionStaticInitProvider","started":"15:28:33.609","dependents":[362],"id":113,"thread":"build-48"},{"duration":0,"stepId":"io.quarkus.deployment.steps.MainClassBuildStep#applicationReflection","started":"15:28:33.603","dependents":[412],"id":71,"thread":"build-18"},{"duration":0,"stepId":"io.quarkus.arc.deployment.TestsAsBeansProcessor#testAnnotations","started":"15:28:33.610","dependents":[337,320,189],"id":120,"thread":"build-52"},{"duration":0,"stepId":"io.quarkus.arc.deployment.ReflectiveBeanClassesProcessor#implicitReflectiveBeanClasses","started":"15:28:34.453","dependents":[366],"id":340,"thread":"build-18"},{"duration":0,"stepId":"io.quarkus.arc.deployment.staticmethods.InterceptedStaticMethodsProcessor#callInitializer","started":"15:28:34.552","dependents":[413],"id":369,"thread":"build-17"},{"duration":0,"stepId":"org.apache.camel.quarkus.core.deployment.CamelNativeImageProcessor#embedSelectResourcesInNativeExecutable","started":"15:28:34.278","dependents":[329],"id":270,"thread":"build-2"},{"duration":0,"stepId":"io.quarkus.vertx.deployment.VertxProcessor#collectEventConsumers","started":"15:28:34.454","dependents":[354,350],"id":343,"thread":"build-3"},{"duration":0,"stepId":"io.quarkus.netty.deployment.NettyProcessor#limitArenaSize","started":"15:28:33.612","dependents":[413],"id":143,"thread":"build-58"},{"duration":0,"stepId":"io.quarkus.arc.deployment.ArcProcessor#validateAsyncObserverExceptionHandlers","started":"15:28:34.483","dependents":[366],"id":360,"thread":"build-26"},{"duration":0,"stepId":"io.quarkus.arc.deployment.TestsAsBeansProcessor#testClassBeans","started":"15:28:33.611","dependents":[337,320],"id":126,"thread":"build-17"},{"duration":0,"stepId":"io.quarkus.deployment.steps.PreloadClassesBuildStep#registerPreInitClasses","started":"15:28:33.600","dependents":[],"id":57,"thread":"build-29"},{"duration":0,"stepId":"io.quarkus.smallrye.context.deployment.SmallRyeContextPropagationProcessor#createSynthBeansForConfiguredInjectionPoints","started":"15:28:34.454","dependents":[351,413,353,352],"id":342,"thread":"build-18"},{"duration":0,"stepId":"org.apache.camel.quarkus.component.platform.http.deployment.PlatformHttpProcessor#platformHttpRouterBean","started":"15:28:37.819","dependents":[413,402],"id":401,"thread":"build-66"},{"duration":0,"stepId":"io.quarkus.undertow.deployment.UndertowStaticResourcesBuildStep#handleGeneratedWebResources","started":"15:28:33.633","dependents":[],"id":166,"thread":"build-67"},{"duration":0,"stepId":"org.apache.camel.quarkus.component.rest.deployment.RestProcessor#feature","started":"15:28:33.598","dependents":[413],"id":50,"thread":"build-29"},{"duration":0,"stepId":"io.quarkus.deployment.steps.BannerProcessor#watchBannerChanges","started":"15:28:33.610","dependents":[223],"id":124,"thread":"build-33"},{"duration":0,"stepId":"io.quarkus.arc.deployment.ArcProcessor#exposeCustomScopeNames","started":"15:28:33.606","dependents":[332,349,337,142,323,326,320,189,292],"id":95,"thread":"build-5"},{"duration":0,"stepId":"io.quarkus.deployment.steps.ShutdownListenerBuildStep#setupShutdown","started":"15:28:37.821","dependents":[413],"id":406,"thread":"build-66"},{"duration":0,"stepId":"io.quarkus.vertx.deployment.EventBusCodecProcessor#registerCodecs","started":"15:28:34.308","dependents":[350,412],"id":325,"thread":"build-39"},{"duration":0,"stepId":"io.quarkus.arc.deployment.BuildTimeEnabledProcessor#ifBuildProfile","started":"15:28:34.282","dependents":[294,332],"id":282,"thread":"build-25"},{"duration":0,"stepId":"org.apache.camel.quarkus.core.deployment.main.CamelMainProcessor#indexCamelMainApplication","started":"15:28:33.604","dependents":[273],"id":76,"thread":"build-41"},{"duration":0,"stepId":"io.quarkus.deployment.dev.testing.TestTracingProcessor#handle","started":"15:28:33.606","dependents":[145,327],"id":93,"thread":"build-46"},{"duration":0,"stepId":"io.quarkus.deployment.dev.ConfigureDisableInstrumentationBuildStep#configure","started":"15:28:33.606","dependents":[409,410],"id":96,"thread":"build-45"},{"duration":0,"stepId":"io.quarkus.arc.deployment.ConfigBuildStep#registerCustomConfigBeanTypes","started":"15:28:34.454","dependents":[351,353,352,412],"id":344,"thread":"build-51"},{"duration":0,"stepId":"io.quarkus.vertx.http.deployment.devmode.console.DevConsoleProcessor#setupDevConsoleWebjar","started":"15:28:33.601","dependents":[262],"id":64,"thread":"build-29"},{"duration":0,"stepId":"io.quarkus.arc.deployment.BuildTimeEnabledProcessor#conditionTransformer","started":"15:28:34.283","dependents":[337],"id":294,"thread":"build-17"},{"duration":0,"stepId":"org.apache.camel.quarkus.core.deployment.CamelRegistryProcessor#bindRuntimeBeansToRegistry","started":"15:28:37.819","dependents":[413,403],"id":402,"thread":"build-7"},{"duration":0,"stepId":"io.quarkus.deployment.steps.CurateOutcomeBuildStep#curateOutcome","started":"15:28:33.611","dependents":[163,392,376,203,296,309,262,268,396,397,408,152,189,256,155],"id":141,"thread":"build-33"},{"duration":0,"stepId":"io.quarkus.arc.deployment.ConfigBuildStep#registerConfigMappingsBean","started":"15:28:34.454","dependents":[354],"id":341,"thread":"build-26"},{"duration":0,"stepId":"io.quarkus.deployment.steps.ConfigGenerationBuildStep#extensionMappings","started":"15:28:34.282","dependents":[362,339,358,341,357,412],"id":278,"thread":"build-14"},{"duration":0,"stepId":"io.quarkus.resteasy.deployment.ResteasyServletProcessor#addServletsToExceptionMapper","started":"15:28:34.554","dependents":[413],"id":375,"thread":"build-50"},{"duration":0,"stepId":"io.quarkus.arc.deployment.StartupBuildSteps#registerStartupObservers","started":"15:28:34.466","dependents":[356],"id":355,"thread":"build-62"},{"duration":0,"stepId":"org.apache.camel.quarkus.core.deployment.CamelProcessor#coreServiceFilter","started":"15:28:33.611","dependents":[383],"id":128,"thread":"build-59"},{"duration":0,"stepId":"org.apache.camel.quarkus.component.dsl.modeline.deployment.DslModelineProcessor#addPropertyTrait","started":"15:28:34.558","dependents":[413],"id":378,"thread":"build-62"},{"duration":0,"stepId":"io.quarkus.arc.deployment.ObserverValidationProcessor#validateApplicationObserver","started":"15:28:34.483","dependents":[366],"id":361,"thread":"build-18"},{"duration":0,"stepId":"io.quarkus.arc.deployment.ConfigBuildStep#validateConfigPropertiesInjectionPoints","started":"15:28:34.483","dependents":[363],"id":357,"thread":"build-57"},{"duration":0,"stepId":"org.apache.camel.quarkus.support.httpclient.deployment.HttpClientProcessor#suffixListResource","started":"15:28:33.589","dependents":[329],"id":15,"thread":"build-4"},{"duration":0,"stepId":"io.quarkus.kafka.client.deployment.KafkaProcessor#silenceUnwantedConfigLogs","started":"15:28:33.604","dependents":[145,327],"id":85,"thread":"build-11"},{"duration":0,"stepId":"io.quarkus.arc.deployment.HotDeploymentConfigBuildStep#configFile","started":"15:28:33.595","dependents":[223],"id":38,"thread":"build-16"},{"duration":0,"stepId":"io.quarkus.arc.deployment.ConfigBuildStep#validateConfigValues","started":"15:28:34.552","dependents":[413,412],"id":368,"thread":"build-62"},{"duration":0,"stepId":"io.quarkus.vertx.http.deployment.VertxHttpProcessor#notFoundRoutes","started":"15:28:37.818","dependents":[399],"id":398,"thread":"build-66"},{"duration":0,"stepId":"io.quarkus.deployment.SslProcessor#setupNativeSsl","started":"15:28:33.610","dependents":[311],"id":130,"thread":"build-16"},{"duration":0,"stepId":"io.quarkus.kubernetes.deployment.KnativeProcessor#createLabels","started":"15:28:33.609","dependents":[261,199,260],"id":112,"thread":"build-43"},{"duration":0,"stepId":"io.quarkus.jackson.deployment.JacksonProcessor#autoRegisterModules","started":"15:28:34.281","dependents":[304],"id":277,"thread":"build-15"},{"duration":0,"stepId":"org.apache.camel.quarkus.component.direct.deployment.DirectProcessor#feature","started":"15:28:33.601","dependents":[413],"id":66,"thread":"build-11"},{"duration":0,"stepId":"io.quarkus.kubernetes.deployment.KubernetesProcessor#produceFeature","started":"15:28:33.593","dependents":[413],"id":33,"thread":"build-16"},{"duration":0,"stepId":"io.quarkus.resteasy.deployment.ResteasyServletProcessor#build","started":"15:28:34.553","dependents":[413,375,412],"id":371,"thread":"build-17"},{"duration":0,"stepId":"org.apache.camel.quarkus.support.httpclient.deployment.HttpClientProcessor#registerForReflection","started":"15:28:34.281","dependents":[412],"id":284,"thread":"build-35"},{"duration":0,"stepId":"org.apache.camel.quarkus.support.commons.logging.deployment.CommonsLoggingSupportProcessor#reflectiveClasses","started":"15:28:33.595","dependents":[412],"id":43,"thread":"build-14"},{"duration":0,"stepId":"org.apache.camel.quarkus.component.http.deployment.HttpProcessor#feature","started":"15:28:33.595","dependents":[413],"id":42,"thread":"build-16"},{"duration":0,"stepId":"io.quarkus.resteasy.common.deployment.ResteasyCommonProcessor#setupGzipProviders","started":"15:28:33.625","dependents":[330],"id":160,"thread":"build-67"},{"duration":0,"stepId":"io.quarkus.kubernetes.deployment.OpenshiftProcessor#createLabels","started":"15:28:33.608","dependents":[261,199,260],"id":109,"thread":"build-50"},{"duration":0,"stepId":"io.quarkus.arc.deployment.ConfigBuildStep#registerConfigPropertiesBean","started":"15:28:34.453","dependents":[354],"id":339,"thread":"build-57"},{"duration":0,"stepId":"io.quarkus.resteasy.common.deployment.ResteasyCommonProcessor#registerJsonContextResolvers","started":"15:28:34.282","dependents":[330,356,358,337,320],"id":285,"thread":"build-33"},{"duration":0,"stepId":"io.quarkus.vertx.core.deployment.VertxCoreProcessor#filterNettyHostsFileParsingWarn","started":"15:28:33.602","dependents":[145,327],"id":70,"thread":"build-36"},{"duration":0,"stepId":"org.apache.camel.quarkus.component.log.deployment.LogProcessor#feature","started":"15:28:33.598","dependents":[413],"id":51,"thread":"build-29"},{"duration":0,"stepId":"org.apache.camel.quarkus.core.deployment.ConsumeProcessor#generateConsumeRoutes","started":"15:28:34.558","dependents":[413],"id":380,"thread":"build-59"},{"duration":0,"stepId":"io.quarkus.arc.deployment.ConfigBuildStep#generateConfigClasses","started":"15:28:34.282","dependents":[362,339,358,341,357,412],"id":279,"thread":"build-4"},{"duration":0,"stepId":"io.quarkus.arc.deployment.staticmethods.InterceptedStaticMethodsProcessor#processInterceptedStaticMethods","started":"15:28:34.455","dependents":[376,412],"id":346,"thread":"build-51"},{"duration":0,"stepId":"io.quarkus.vertx.deployment.VertxProcessor#build","started":"15:28:34.455","dependents":[401,409,413,410,412],"id":350,"thread":"build-18"},{"duration":0,"stepId":"io.quarkus.vertx.http.deployment.VertxHttpProcessor#openSocket","started":"15:28:38.430","dependents":[413,412],"id":411,"thread":"build-62"},{"duration":0,"stepId":"io.quarkus.arc.deployment.AutoInjectFieldProcessor#annotationTransformer","started":"15:28:34.309","dependents":[337],"id":324,"thread":"build-27"},{"duration":0,"stepId":"io.quarkus.deployment.steps.ApplicationInfoBuildStep#create","started":"15:28:33.611","dependents":[413,261,196,199,174,260,176,175,213,385,170],"id":134,"thread":"build-57"},{"duration":0,"stepId":"io.quarkus.deployment.logging.LoggingResourceProcessor#setUpDefaultLevels","started":"15:28:33.606","dependents":[391,327],"id":102,"thread":"build-30"},{"duration":0,"stepId":"io.quarkus.arc.deployment.ArcProcessor#signalBeanContainerReady","started":"15:28:34.551","dependents":[404,373,370,413,369,410,379,377,368,403],"id":367,"thread":"build-5"},{"duration":0,"stepId":"org.apache.camel.quarkus.component.kafka.deployment.KafkaProcessor#createKafkaClientFactoryProducerBean","started":"15:28:33.633","dependents":[337,320],"id":165,"thread":"build-6"},{"duration":0,"stepId":"io.quarkus.deployment.pkg.steps.PackageTypeVerificationBuildStep#builtins","started":"15:28:33.607","dependents":[156],"id":101,"thread":"build-35"},{"duration":0,"stepId":"io.quarkus.container.image.openshift.deployment.OpenshiftProcessor#availability","started":"15:28:33.598","dependents":[62],"id":52,"thread":"build-25"},{"duration":0,"stepId":"org.apache.camel.quarkus.core.deployment.CamelFeature#feature","started":"15:28:33.587","dependents":[413],"id":10,"thread":"build-5"},{"duration":0,"stepId":"io.quarkus.resteasy.deployment.RestPathAnnotationProcessor#registerBeanClasses","started":"15:28:33.633","dependents":[337,320],"id":167,"thread":"build-59"},{"duration":0,"stepId":"org.apache.camel.quarkus.core.deployment.CamelProcessor#coreServicePatterns","started":"15:28:33.604","dependents":[328,318,383],"id":82,"thread":"build-17"},{"duration":0,"stepId":"io.quarkus.deployment.steps.ReflectionDiagnosticProcessor#writeReflectionData","started":"15:28:38.431","dependents":[],"id":412,"thread":"build-39"},{"duration":0,"stepId":"io.quarkus.caffeine.deployment.CaffeineProcessor#cacheLoaders","started":"15:28:34.281","dependents":[412],"id":276,"thread":"build-2"},{"duration":0,"stepId":"org.apache.camel.quarkus.component.dsl.modeline.deployment.DslModelineProcessor#feature","started":"15:28:33.599","dependents":[413],"id":54,"thread":"build-29"}],"started":"2023-06-19T15:28:33.572","buildTarget":"quarkus-dems-adapter-1.0-SNAPSHOT"}