{
    "name": "Frank, Joe Mike Joh - 2",
    "key": "50442.0734.2",
    "description": "",
    "timeZoneId": "Pacific Standard Time",
    "templateCase": "28",
    "fields": [
        {
            "id": 12,
            "value": "50442.0734.2"
        },
        {
            "id": 3,
            "value": "22-472002"
        },
        {
            "id": 13,
            "value": "2022-08-25"
        },
        {
            "id": 9,
            "value": "Garrison, Dave"
        },
        {
            "id": 14,
            "value": null
        },
        {
            "id": 18,
            "value": "CCC 344 Robbery, CCC 134 Statements not specially permitted"
        },
        {
            "id": 24,
            "value": "105: Kelowna Municipal RCMP"
        },
        {
            "id": 25,
            "value": "Rhodes, Christopher 1001"
        },
        {
            "id": 26,
            "value": "C402: Kelowna Crown Counsel"
        },
        {
            "id": 28,
            "value": [
                "Indigenous"
            ]
        },
        {
            "id": 29,
            "value": "2022-08-25"
        },
        {
            "id": 30,
            "value": "2022-08-26"
        },
        {
            "id": 31,
            "value": "Frank, Joe Mike John AN"
        }
    ]
}